fit9133/__init__.py
fit9133/letter_price_info.json
fit9133/parcel_price_info.json
fit9133/stamp.py
fit9133/zone_country_info.json
gdds_fit9133-1.1.dist-info/METADATA
gdds_fit9133-1.1.dist-info/WHEEL
gdds_fit9133-1.1.dist-info/top_level.txt
gdds_fit9133-1.1.dist-info/RECORD
