Metadata-Version: 2.1
Name: gdds-fit9133
Version: 1.1
Summary: fit9133 module
Home-page: UNKNOWN
Author: lei yang
Author-email: lei.yang@monash.edu
License: UNKNOWN
Platform: UNKNOWN
Classifier: Programming Language :: Python :: 3
Classifier: License :: OSI Approved :: MIT License
Classifier: Operating System :: OS Independent
